data_path_config/__init__.py
data_path_config/path.py
data_path_config/cloudflare/__init__.py
data_path_config/cloudflare/boto3_client.py
data_path_config/cloudflare/requests_client.py
data_path_config/google/__init__.py
data_path_config/google/bigquery.py
data_path_config/google/drive.py
data_path_config/google/sheet.py
data_path_config-0.6.5.dist-info/licenses/LICENSE
data_path_config-0.6.5.dist-info/METADATA
data_path_config-0.6.5.dist-info/WHEEL
data_path_config-0.6.5.dist-info/top_level.txt
data_path_config-0.6.5.dist-info/RECORD
