Metadata-Version: 2.4
Name: data-path-config
Version: 0.6.5
Summary: A utility for managing data and log directory paths in Python projects
Home-page: https://github.com/guocity/data-path-config
Author: guocity
Author-email: 
Classifier: Programming Language :: Python :: 3
Classifier: License :: OSI Approved :: MIT License
Classifier: Operating System :: OS Independent
Requires-Python: >=3.6
License-File: LICENSE
Requires-Dist: python-dotenv>=0.19.0
Requires-Dist: gspread
Requires-Dist: gspread-dataframe
Requires-Dist: ratelimit
Requires-Dist: google-api-python-client
Requires-Dist: google-auth
Requires-Dist: requests
Requires-Dist: boto3
Requires-Dist: google-cloud-bigquery
Requires-Dist: pandas
Requires-Dist: pandas_gbq
Dynamic: author
Dynamic: classifier
Dynamic: description
Dynamic: description-content-type
Dynamic: home-page
Dynamic: license-file
Dynamic: requires-dist
Dynamic: requires-python
Dynamic: summary
